fmpupdate/__init__.py
fmpupdate/utils.py
fmpupdate-0.1.1.dist-info/METADATA
fmpupdate-0.1.1.dist-info/WHEEL
fmpupdate-0.1.1.dist-info/top_level.txt
fmpupdate-0.1.1.dist-info/RECORD
