Metadata-Version: 2.4
Name: fmpupdate
Version: 0.1.1
Summary: fmp tools
Author: Hams
Requires-Dist: certifi==2025.4.26
Requires-Dist: charset-normalizer==3.4.2
Requires-Dist: idna==3.10
Requires-Dist: numpy==2.2.6
Requires-Dist: pandas==2.2.3
Requires-Dist: python-dateutil==2.9.0.post0
Requires-Dist: pytz==2025.2
Requires-Dist: requests==2.32.3
Requires-Dist: six==1.17.0
Requires-Dist: tzdata==2025.2
Requires-Dist: urllib3==2.4.0
Dynamic: author
Dynamic: requires-dist
Dynamic: summary
